{"name":"thomas.brisbout","tagline":"developer & web enthusiast","body":"Work Experience\r\n---------------------\r\n\r\n### Software Consultant, [Dassault Systemes Industry Services][DSIS]\r\n#### Nov 2011 - Present\r\n\r\nConsulting for several customer projects for French manufacturers in Aerospace and Automotive industry.\r\nTechnical lead of customer specific development (Requirements, Realization, Deployment).\r\nSupervision of development on specific subject.Key intermediary between R&D teams and customer.\r\nPrototyping and Development of Proof of Concepts for pre-sale activities.\r\nModern web applications development, RESTful web services.\r\nSoftware Factory and Development Environment implementation.\r\n\r\n\r\n### Software Developer, [Keonys][KEONYS]\r\n#### Oct 2009 - Oct 2011\r\n\r\nIn charge of specification, development, deployment and support of the PLM software customizations.\r\nTechnical Expertise on ENOVIA V6.\r\nKey contact with the customer for web issues.\r\n\r\n\r\n### Software Developer, Intern, Dassault Data Services\r\n#### Apr 2009 - Sep 2009\r\n\r\nDevelopment of an applicative security prototype for a cloud deployment of the ENOVIA V6 PLM system.\r\nIndustrialization done and integration in a whole solution sold to aerospace OEMs.\r\n\r\n\r\n### Web Developer, Intern, Meteo Omnium\r\n#### May 2008 - Aug 2008\r\n\r\nRe-design of the company website.\r\nDevelopment of web applications for customer data management.\r\nThis internship led to a fixed-term contract.\r\nPHP - MySQL - ActionScript - Javascript - Web design.\r\n\r\n\r\n### Web Developer, Intern, Skignaletiks\r\n#### May 2007 - Jul 2007\r\n\r\nCreation of the company website.\r\nDevelopment of a web application displaying ski station domain.\r\n\r\n***\r\n\r\nCompetencies\r\n---------------------\r\n\r\n### Current Programming Stack\r\n* Front-end\r\n\t* HTML5 + CSS3 + Javascript\r\n\t* libraries (Bootstrap, Modernizr, jQuery, LESS)\r\n* Back-end\r\n\t* Java (JEE, Spring)\r\n\t* Play2\r\n* Scripting\r\n\t* Shell\r\n\r\n### Software Factory\r\n* Editors: *Eclipse, Sublime Text, Vim*\r\n* Source Code Management: *Git, SVN*\r\n* Build Management: *Maven, Ant*\r\n* Continous Integration: *Jenkins*\r\n* Issue Tracker: *Jira, Mantis, Redmine*\r\n* DevOps: *Chef* \r\n* Virtualization: *VMWare, VirtualBox, Vagrant*\r\n* Operating Systems: *Linux (Ubuntu, openSuse, Red Hat), Windows*\r\n\r\n### Functional\r\nProject Lifecycle Management  \r\nAgile Methods (Scrum, Kanban)  \r\nSOLID Principles  \r\n\r\n\r\n### Languages\r\nFrench (native)  \r\nEnglish (fluent)  \r\n\r\n### Productivity\r\nOffice Tools  \r\nPomodoro Technique  \r\nGTD  \r\n\r\n### Others\r\nDesign (Principles & tools)  \r\n\r\n### Interests\r\nWeb & Mobile Technologies  \r\nComputing & Open Source  \r\nBoard sports  \r\nE-sports  \r\nEvent organization  \r\n\r\n***\r\n\r\nEducation\r\n---------------------\r\n\r\n### Master of Science in Advanced Technology Management, [University of Wolverhampton][WLV]\r\n#### Sep 2008 - Oct 2009\r\n\r\nNew Product Development, CAD/CAM interface, \r\nRapid Prototyping, Research Methods,\r\nSustainability & lifecycle engineering,\r\nStrategic Quality Management. \r\nPostgraduate dissertation about applicative security of a cloud-based PLM Software.\r\n\r\n\r\n### Engineering Degree in Generalized Product Design, [Institute of Advanced Industrial Technology ESTIA][ESTIA]\r\n#### Sep 2006 - Sept 2009 \r\n\r\nProduct Lifecycle Management & Computing Specialization.\r\nTrilingual engineering course in computing, mechanics and electronics.\r\n\r\n\r\n### Preparation for the competitive entrance examinations of French Engineering Schools, A.Artaud High School\r\n#### Sep 2004 - Jul 2006\r\n\r\nIntensive course about mathematics, physics and engineering science.\r\n\r\n\r\n### A-level with distinction in Electrotechnology, G.de Gennes High School\r\n#### 2004\r\n\r\n***\r\n\r\nReferences\r\n---------------------\r\n\r\n### HARMEGNIES Ronan\r\nSenior Software Architect, Dassault Systemes  \r\nTechnical supervisor for 3 years  \r\n<ronan.hargmenies@3ds.com>\r\n\r\n### LAROCHE Fabien\r\nProject Manager, Dassault Systemes  \r\nProject Leader for 3 years  \r\n<fabien.laroche@3ds.com>\r\n\r\n### BOURDAIS Nicolas\r\nFunctional Consultant, Oracle  \r\nFormer internship tutor at Dassault Systemes  \r\n<nicolas.bourdais@oracle.com>\r\n\t\r\n### DUPRAT Guillaume\r\nTechnical account manager, Mediatech\r\nFormer internship tutor at Skignaletiks   \r\n<guillaume.duprat@mediatech.fr>\t\r\n\r\n***\r\n\r\nContact\r\n---------------------\r\n\r\n### Address\r\n85 boulevard Murat  \r\n75016  \r\nFRANCE  \r\n\r\n### Email\r\n<thomas.brisbout@gmail.com>\r\n\r\n### Phone\r\n00 33 6 2992 5560\r\n\r\n\r\n[DSIS]:   <http://www.3ds.com/fr/support-services/services>\r\n[KEONYS]: <http://www.keonys.com/>\r\n[WLV]:    <http://www.wlv.ac.uk>\r\n[ESTIA]:  <http://www.estia.fr>","google":"","note":"Don't delete this file! It's used internally to help with page regeneration."}